encoanalyzer/__init__.py
encoanalyzer/core.py
encoanalyzer-0.1.0.dist-info/licenses/LICENSE
encoanalyzer-0.1.0.dist-info/METADATA
encoanalyzer-0.1.0.dist-info/WHEEL
encoanalyzer-0.1.0.dist-info/entry_points.txt
encoanalyzer-0.1.0.dist-info/top_level.txt
encoanalyzer-0.1.0.dist-info/RECORD
