Metadata-Version: 2.4
Name: encoanalyzer
Version: 0.1.0
Summary: A tool for encoding and analyzing text bytes visually
Home-page: https://github.com/yourusername/encoanalyzer
Author: Adam Alcander
Author-email: aeden6877@gmail.com
License: MIT
Classifier: Programming Language :: Python :: 3
Classifier: License :: OSI Approved :: MIT License
Classifier: Operating System :: OS Independent
Requires-Python: >=3.7
License-File: LICENSE
Requires-Dist: matplotlib
Requires-Dist: numpy
Requires-Dist: colorama
Dynamic: author
Dynamic: description
Dynamic: description-content-type
Dynamic: license
Dynamic: license-file
Dynamic: requires-dist
Dynamic: summary
